kg_kubestatemetrics/__init__.py
kg_kubestatemetrics/builder.py
kg_kubestatemetrics/option.py
kg_kubestatemetrics/py.typed
kg_kubestatemetrics/tests/__init__.py
kg_kubestatemetrics/tests/test_builder.py
tests/__init__.py
tests/test_builder.py
kg_kubestatemetrics-0.8.0.dist-info/LICENSE
kg_kubestatemetrics-0.8.0.dist-info/METADATA
kg_kubestatemetrics-0.8.0.dist-info/WHEEL
kg_kubestatemetrics-0.8.0.dist-info/top_level.txt
kg_kubestatemetrics-0.8.0.dist-info/RECORD
